liveeo/prefect_utils/__init__.py
liveeo/prefect_utils/anyscale/__init__.py
liveeo/prefect_utils/anyscale/compute_config.py
liveeo/prefect_utils/anyscale/infrastructure.py
liveeo/prefect_utils/anyscale/named_anyscale_compute_config.py
liveeo/prefect_utils/anyscale/task_runner.py
liveeo/prefect_utils/aws/__init__.py
liveeo/prefect_utils/aws/batch.py
liveeo/prefect_utils/caching.py
liveeo/prefect_utils/deployments.py
liveeo/prefect_utils/environment.py
liveeo/prefect_utils/logging.py
liveeo/prefect_utils/testing.py
liveeo_prefect_utils-3.3.0.dist-info/METADATA
liveeo_prefect_utils-3.3.0.dist-info/WHEEL
liveeo_prefect_utils-3.3.0.dist-info/RECORD
